backports/__init__.py
backports/asyncio/__init__.py
backports/asyncio/runners.py
busypie/__init__.py
busypie/awaiter.py
busypie/checker.py
busypie/condition.py
busypie/core.py
busypie/durations.py
busypie/func.py
busypie/runner.py
busypie/time.py
busypie/types.py
busypie-0.5.1.dist-info/LICENSE
busypie-0.5.1.dist-info/METADATA
busypie-0.5.1.dist-info/WHEEL
busypie-0.5.1.dist-info/top_level.txt
busypie-0.5.1.dist-info/RECORD
