Metadata-Version: 2.1
Name: busypie
Version: 0.5.1
Summary: Easy and expressive busy-waiting for Python
Home-page: https://github.com/rockem/busypie
Author: Eli Segal
Author-email: eli.segal@gmail.com
License: Apache License 2.0
Keywords: busy wait tdd test builder sleep wait pytest
Classifier: Programming Language :: Python :: 3
Classifier: License :: OSI Approved :: Apache Software License
Classifier: Operating System :: OS Independent
Requires-Python: >=3.6
License-File: LICENSE
